odoo/addons/fieldservice_stage_server_action/README.rst
odoo/addons/fieldservice_stage_server_action/__init__.py
odoo/addons/fieldservice_stage_server_action/__manifest__.py
odoo/addons/fieldservice_stage_server_action/data/base_automation.xml
odoo/addons/fieldservice_stage_server_action/data/fsm_stage.xml
odoo/addons/fieldservice_stage_server_action/data/ir_server_action.xml
odoo/addons/fieldservice_stage_server_action/i18n/de.po
odoo/addons/fieldservice_stage_server_action/i18n/es.po
odoo/addons/fieldservice_stage_server_action/i18n/es_AR.po
odoo/addons/fieldservice_stage_server_action/i18n/es_CL.po
odoo/addons/fieldservice_stage_server_action/i18n/fieldservice_stage_server_action.pot
odoo/addons/fieldservice_stage_server_action/i18n/it.po
odoo/addons/fieldservice_stage_server_action/i18n/pt_BR.po
odoo/addons/fieldservice_stage_server_action/models/__init__.py
odoo/addons/fieldservice_stage_server_action/models/fsm_order.py
odoo/addons/fieldservice_stage_server_action/models/fsm_stage.py
odoo/addons/fieldservice_stage_server_action/readme/CONFIGURE.md
odoo/addons/fieldservice_stage_server_action/readme/CONTRIBUTORS.md
odoo/addons/fieldservice_stage_server_action/readme/DESCRIPTION.md
odoo/addons/fieldservice_stage_server_action/readme/USAGE.md
odoo/addons/fieldservice_stage_server_action/static/description/icon.png
odoo/addons/fieldservice_stage_server_action/static/description/icon.svg
odoo/addons/fieldservice_stage_server_action/static/description/index.html
odoo/addons/fieldservice_stage_server_action/tests/__init__.py
odoo/addons/fieldservice_stage_server_action/tests/test_fsm_order_run_action.py
odoo/addons/fieldservice_stage_server_action/views/fsm_stage.xml
odoo_addon_fieldservice_stage_server_action-18.0.1.1.0.2.dist-info/METADATA
odoo_addon_fieldservice_stage_server_action-18.0.1.1.0.2.dist-info/WHEEL
odoo_addon_fieldservice_stage_server_action-18.0.1.1.0.2.dist-info/top_level.txt
odoo_addon_fieldservice_stage_server_action-18.0.1.1.0.2.dist-info/RECORD
